{
  "_meta": {
    "city": "khanh-hoa-phan-rang",
    "last_updated": "2026-06-25",
    "agent_task": "T-004",
    "status": "completed",
    "missing_fields": [],
    "data_sources": [
      "Ẩm thực địa phương Ninh Thuận"
    ]
  },
  "data": [
    {
      "id": "019f2b3c-4d5e-7a8b-b2c3-d4e5f6000201",
      "name": "Bánh căn Phan Rang",
      "type": "dish",
      "description": "Bánh đổ trong khuôn đất nung, nhân trứng, mực hoặc tôm, ăn kèm nước mắm đậu phộng hoặc mắm nêm đặc quánh."
    },
    {
      "id": "019f2b3c-4d5e-7a8b-b2c3-d4e5f6000202",
      "name": "Cơm gà Phan Rang",
      "type": "dish",
      "description": "Gà thả vườn thịt dai ngọt, cơm nấu bằng nước luộc gà béo ngậy, ăn kèm nước mắm gừng hoặc muối ớt đặc chế."
    },
    {
      "id": "019f2b3c-4d5e-7a8b-b2c3-d4e5f6000203",
      "name": "Bánh xèo Phan Rang",
      "type": "dish",
      "description": "Kích thước nhỏ gọn, đổ khuôn đất, ngập tràn hải sản tươi rói và ăn bằng cách nhúng nguyên bánh vào tô nước chấm."
    },
    {
      "id": "019f2b3c-4d5e-7a8b-b2c3-d4e5f6000204",
      "name": "Thịt cừu Ninh Thuận",
      "type": "specialty",
      "description": "Thịt cừu chăn thả tự nhiên, thớ thịt mọng nước, thường được nướng tẩm gia vị thảo mộc hoặc nấu lagu."
    },
    {
      "id": "019f2b3c-4d5e-7a8b-b2c3-d4e5f6000205",
      "name": "Nho và Vang nho Phan Rang",
      "type": "specialty",
      "description": "Nho đỏ, nho xanh vị ngọt thanh giòn đặc trưng mọc trên vùng đất cát đầy nắng gió."
    }
  ]
}